aliyunsdkdocumentautoml/__init__.py
aliyunsdkdocumentautoml/request/__init__.py
aliyunsdkdocumentautoml/request/v20221229/CreateModelAsyncPredictRequest.py
aliyunsdkdocumentautoml/request/v20221229/GetModelAsyncPredictRequest.py
aliyunsdkdocumentautoml/request/v20221229/PredictClassifierModelRequest.py
aliyunsdkdocumentautoml/request/v20221229/PredictModelRequest.py
aliyunsdkdocumentautoml/request/v20221229/PredictTemplateModelRequest.py
aliyunsdkdocumentautoml/request/v20221229/__init__.py
aliyun_python_sdk_documentautoml-1.0.0.dist-info/LICENSE
aliyun_python_sdk_documentautoml-1.0.0.dist-info/METADATA
aliyun_python_sdk_documentautoml-1.0.0.dist-info/WHEEL
aliyun_python_sdk_documentautoml-1.0.0.dist-info/top_level.txt
aliyun_python_sdk_documentautoml-1.0.0.dist-info/RECORD
